{"width":256,"imagePath":"weapon_tex.png","height":512,"name":"weapon","SubTexture":[{"frameHeight":70,"y":140,"frameX":-7,"width":208,"frameY":-5,"height":60,"name":"weapon/gun_3","frameWidth":220,"x":1},{"frameHeight":90,"y":1,"frameX":-9,"width":206,"frameY":-7,"height":78,"name":"weapon/weapon_5","frameWidth":220,"x":1},{"frameHeight":60,"y":202,"frameX":-13,"width":200,"frameY":-3,"height":52,"name":"weapon/weapon_4","frameWidth":220,"x":1},{"frameHeight":60,"y":256,"frameX":-7,"width":111,"frameY":-3,"height":56,"name":"weapon/gun_1","frameWidth":120,"x":1},{"frameHeight":60,"y":81,"frameX":-9,"width":228,"frameY":-2,"height":57,"name":"weapon/gun_2","frameWidth":240,"x":1},{"frameHeight":40,"y":369,"frameX":-7,"width":101,"frameY":-4,"height":32,"name":"weapon/weapon_6","frameWidth":110,"x":1},{"frameHeight":60,"y":314,"frameX":-8,"width":98,"frameY":-8,"height":46,"name":"fire/fire_2","frameWidth":110,"x":1},{"frameHeight":60,"y":314,"frameX":-15,"width":85,"frameY":-2,"height":53,"name":"fire/fire_3","frameWidth":110,"x":101},{"frameHeight":60,"y":256,"frameX":-2,"width":107,"frameY":-1,"height":56,"name":"fire/fire_1","frameWidth":110,"x":114}]}